alexandria/__init__.py
alexandria_ai-0.25.4.25.dist-info/METADATA
alexandria_ai-0.25.4.25.dist-info/WHEEL
alexandria_ai-0.25.4.25.dist-info/RECORD
